[{"id":"07452607645aeeb7","type":"tab","label":"[debug] type hadling of JSONata reslults","disabled":false,"info":"Ensure that the corrent format type is set for the results of the JSONata expression.","env":[]},{"id":"bffb78cb1ac976a2","type":"group","z":"07452607645aeeb7","name":"appending hash/map to string does not work in JSONata","style":{"label":true},"nodes":["2bea31d3828bc60c","340a0798b871641f","b2f66cf4694a1f60","26cca2c2fb5c36aa","415733697ed0abbf","f2979b9a3d787354"],"x":85,"y":806,"w":751,"h":278},{"id":"fbed45b6963bab39","type":"group","z":"07452607645aeeb7","name":"always string because JSONata converts to string","style":{"label":true},"nodes":["9a574c543df17059","05aa6a4218f4e846","ffd75ed0d76ac539","a541e66eca84817d","b75a71a46914f437","384b559b03a12628","4ebbcaa7ee91744f"],"x":92,"y":479,"w":724,"h":301},{"id":"9a574c543df17059","type":"inject","z":"07452607645aeeb7","g":"fbed45b6963bab39","name":"","props":[{"p":"payload"},{"p":"topic","vt":"str"}],"repeat":"","crontab":"","once":false,"onceDelay":0.1,"topic":"","payload":"252457650000","payloadType":"num","x":222,"y":520,"wires":[["05aa6a4218f4e846"]]},{"id":"05aa6a4218f4e846","type":"debug","z":"07452607645aeeb7","g":"fbed45b6963bab39","name":"debug 1","active":true,"tosidebar":true,"console":false,"tostatus":false,"complete":"$toString($$.payload & \"apart\")","targetType":"jsonata","statusVal":"","statusType":"auto","x":485,"y":520,"wires":[]},{"id":"ffd75ed0d76ac539","type":"inject","z":"07452607645aeeb7","g":"fbed45b6963bab39","name":"","props":[{"p":"payload"},{"p":"topic","vt":"str"}],"repeat":"","crontab":"","once":false,"onceDelay":0.1,"topic":"","payload":"[1,2,3,4,5]","payloadType":"json","x":202,"y":604.5,"wires":[["05aa6a4218f4e846"]]},{"id":"a541e66eca84817d","type":"inject","z":"07452607645aeeb7","g":"fbed45b6963bab39","name":"","props":[{"p":"payload"},{"p":"topic","vt":"str"}],"repeat":"","crontab":"","once":false,"onceDelay":0.1,"topic":"","payload":"\"ddd\"","payloadType":"json","x":192,"y":688,"wires":[["05aa6a4218f4e846"]]},{"id":"b75a71a46914f437","type":"ut-assert-debug","z":"07452607645aeeb7","g":"fbed45b6963bab39","name":"","nodeid":"05aa6a4218f4e846","msgtype":"normal","inverse":false,"x":561,"y":614,"wires":[["384b559b03a12628"]]},{"id":"5f7b2ae4244160d3","type":"inject","z":"07452607645aeeb7","name":"","props":[{"p":"payload"},{"p":"topic","vt":"str"}],"repeat":"","crontab":"","once":false,"onceDelay":0.1,"topic":"","payload":"252457650000","payloadType":"num","x":1087,"y":189,"wires":[["f3a0419d04ed4222"]]},{"id":"f3a0419d04ed4222","type":"debug","z":"07452607645aeeb7","name":"debug 4","active":true,"tosidebar":true,"console":false,"tostatus":false,"complete":"$$.payload","targetType":"jsonata","statusVal":"","statusType":"auto","x":1070,"y":237,"wires":[]},{"id":"5d63579344ca7e87","type":"ut-assert-debug","z":"07452607645aeeb7","name":"","nodeid":"f3a0419d04ed4222","msgtype":"normal","inverse":false,"x":1151,"y":292,"wires":[["a035f292b851a76e"]]},{"id":"2bea31d3828bc60c","type":"debug","z":"07452607645aeeb7","g":"bffb78cb1ac976a2","name":"debug 6","active":true,"tosidebar":true,"console":false,"tostatus":false,"complete":"$toString($$.payload & \"apart\")","targetType":"jsonata","statusVal":"","statusType":"auto","x":256,"y":916.25,"wires":[]},{"id":"340a0798b871641f","type":"inject","z":"07452607645aeeb7","g":"bffb78cb1ac976a2","name":"","props":[{"p":"payload"},{"p":"topic","vt":"str"}],"repeat":"","crontab":"","once":false,"onceDelay":0.1,"topic":"","payload":"{\"d\":\"d\"}","payloadType":"json","x":191,"y":847,"wires":[["2bea31d3828bc60c"]]},{"id":"b2f66cf4694a1f60","type":"catch","z":"07452607645aeeb7","g":"bffb78cb1ac976a2","name":"","scope":["2bea31d3828bc60c"],"uncaught":false,"x":318,"y":985.5,"wires":[["26cca2c2fb5c36aa"]]},{"id":"26cca2c2fb5c36aa","type":"ut-assert-failure","z":"07452607645aeeb7","g":"bffb78cb1ac976a2","name":"","x":598,"y":985.5,"wires":[]},{"id":"415733697ed0abbf","type":"ut-assert-debug","z":"07452607645aeeb7","g":"bffb78cb1ac976a2","name":"","nodeid":"2bea31d3828bc60c","msgtype":"normal","inverse":false,"x":418,"y":1043,"wires":[["f2979b9a3d787354"]]},{"id":"f2979b9a3d787354","type":"ut-assert-values","z":"07452607645aeeb7","g":"bffb78cb1ac976a2","name":"","ignore_failure_if_succeed":false,"rules":[{"t":"eql","p":"payload.msg","pt":"msg","to":"Invalid JSONata expression: badarg (<<\"$toString($$.payload & \\\"apart\\\")\">>)","tot":"str"}],"x":700,"y":1043,"wires":[[]]},{"id":"384b559b03a12628","type":"ut-assert-values","z":"07452607645aeeb7","g":"fbed45b6963bab39","name":"","ignore_failure_if_succeed":false,"rules":[{"t":"eql","p":"payload.format","pt":"msg","to":"string","tot":"str"}],"x":680,"y":736,"wires":[[]]},{"id":"4ebbcaa7ee91744f","type":"inject","z":"07452607645aeeb7","g":"fbed45b6963bab39","name":"","props":[{"p":"payload"},{"p":"topic","vt":"str"}],"repeat":"","crontab":"","once":false,"onceDelay":0.1,"topic":"","payload":"1.123","payloadType":"num","x":188,"y":739,"wires":[["05aa6a4218f4e846"]]},{"id":"6b1554f4f74b1805","type":"debug","z":"07452607645aeeb7","name":"debug 3","active":true,"tosidebar":true,"console":false,"tostatus":false,"complete":"$$.payload","targetType":"jsonata","statusVal":"","statusType":"auto","x":1130,"y":455,"wires":[]},{"id":"c437d84fbae30b7c","type":"inject","z":"07452607645aeeb7","name":"","props":[{"p":"payload"},{"p":"topic","vt":"str"}],"repeat":"","crontab":"","once":false,"onceDelay":0.1,"topic":"","payload":"{\"d\":\"d\"}","payloadType":"json","x":1080,"y":404,"wires":[["6b1554f4f74b1805"]]},{"id":"b514b39670fd62d6","type":"ut-assert-debug","z":"07452607645aeeb7","name":"","nodeid":"6b1554f4f74b1805","msgtype":"normal","inverse":false,"x":1210,"y":524,"wires":[["a6e2ccd2e332dbcd"]]},{"id":"6dd0d2a212c62666","type":"debug","z":"07452607645aeeb7","name":"debug 7","active":true,"tosidebar":true,"console":false,"tostatus":false,"complete":"$$.payload","targetType":"jsonata","statusVal":"","statusType":"auto","x":1139,"y":679,"wires":[]},{"id":"0e952db2b13797ba","type":"inject","z":"07452607645aeeb7","name":"","props":[{"p":"payload"},{"p":"topic","vt":"str"}],"repeat":"","crontab":"","once":false,"onceDelay":0.1,"topic":"","payload":"[1,2,3,4,5]","payloadType":"json","x":1083,"y":630,"wires":[["6dd0d2a212c62666"]]},{"id":"8dbb1864d191a8bd","type":"ut-assert-debug","z":"07452607645aeeb7","name":"","nodeid":"6dd0d2a212c62666","msgtype":"normal","inverse":false,"x":1219,"y":748,"wires":[["ab9c55e84b9f6c15"]]},{"id":"aabf09218c1ae0d4","type":"debug","z":"07452607645aeeb7","name":"debug 9","active":true,"tosidebar":true,"console":false,"tostatus":false,"complete":"$$.payload","targetType":"jsonata","statusVal":"","statusType":"auto","x":1144,"y":918,"wires":[]},{"id":"b0dfd8b253bc035b","type":"inject","z":"07452607645aeeb7","name":"","props":[{"p":"payload"},{"p":"topic","vt":"str"}],"repeat":"","crontab":"","once":false,"onceDelay":0.1,"topic":"","payload":"\"ddd\"","payloadType":"json","x":1075,"y":870,"wires":[["aabf09218c1ae0d4"]]},{"id":"9ea41437d97547bc","type":"ut-assert-debug","z":"07452607645aeeb7","name":"","nodeid":"aabf09218c1ae0d4","msgtype":"normal","inverse":false,"x":1224,"y":987,"wires":[["a3595ef7f66f5a4a"]]},{"id":"a035f292b851a76e","type":"ut-assert-values","z":"07452607645aeeb7","name":"","ignore_failure_if_succeed":false,"rules":[{"t":"eql","p":"payload.format","pt":"msg","to":"number","tot":"str"}],"x":1507,"y":294,"wires":[[]]},{"id":"a6e2ccd2e332dbcd","type":"ut-assert-values","z":"07452607645aeeb7","name":"","ignore_failure_if_succeed":false,"rules":[{"t":"eql","p":"payload.format","pt":"msg","to":"Object","tot":"str"}],"x":1515,"y":467,"wires":[[]]},{"id":"ab9c55e84b9f6c15","type":"ut-assert-values","z":"07452607645aeeb7","name":"","ignore_failure_if_succeed":false,"rules":[{"t":"eql","p":"payload.format","pt":"msg","to":"array","tot":"str"}],"x":1467,"y":687,"wires":[[]]},{"id":"a3595ef7f66f5a4a","type":"ut-assert-values","z":"07452607645aeeb7","name":"","ignore_failure_if_succeed":false,"rules":[{"t":"eql","p":"payload.format","pt":"msg","to":"string","tot":"str"}],"x":1489,"y":927,"wires":[[]]}]